jay_sdk_test/__init__.py
jay_sdk_test/api_client.py
jay_sdk_test/api_response.py
jay_sdk_test/configuration.py
jay_sdk_test/exceptions.py
jay_sdk_test/py.typed
jay_sdk_test/rest.py
jay_sdk_test/api/__init__.py
jay_sdk_test/api/admin_api.py
jay_sdk_test/api/auth_api.py
jay_sdk_test/api/datasets_api.py
jay_sdk_test/api/default_api.py
jay_sdk_test/api/elastic_search_api.py
jay_sdk_test/api/instruments_api.py
jay_sdk_test/api/jobs_api.py
jay_sdk_test/api/logbooks_api.py
jay_sdk_test/api/origdatablocks_api.py
jay_sdk_test/api/policies_api.py
jay_sdk_test/api/proposals_api.py
jay_sdk_test/api/published_data_api.py
jay_sdk_test/api/samples_api.py
jay_sdk_test/api/user_identities_api.py
jay_sdk_test/api/users_api.py
jay_sdk_test/models/__init__.py
jay_sdk_test/models/attachment.py
jay_sdk_test/models/create_attachment_dto.py
jay_sdk_test/models/create_custom_jwt.py
jay_sdk_test/models/create_dataset_datablock_dto.py
jay_sdk_test/models/create_dataset_orig_datablock_dto.py
jay_sdk_test/models/create_derived_dataset_obsolete_dto.py
jay_sdk_test/models/create_instrument_dto.py
jay_sdk_test/models/create_job_dto.py
jay_sdk_test/models/create_measurement_period_dto.py
jay_sdk_test/models/create_orig_datablock_dto.py
jay_sdk_test/models/create_policy_dto.py
jay_sdk_test/models/create_proposal_dto.py
jay_sdk_test/models/create_published_data_dto.py
jay_sdk_test/models/create_raw_dataset_obsolete_dto.py
jay_sdk_test/models/create_sample_dto.py
jay_sdk_test/models/create_sub_attachment_dto.py
jay_sdk_test/models/create_user_jwt.py
jay_sdk_test/models/create_user_settings_dto.py
jay_sdk_test/models/credentials_dto.py
jay_sdk_test/models/data_file.py
jay_sdk_test/models/datablock.py
jay_sdk_test/models/dataset_class.py
jay_sdk_test/models/datasets_controller_create_request.py
jay_sdk_test/models/datasets_controller_find_by_id_and_replace_request.py
jay_sdk_test/models/datasets_controller_find_by_id_and_update_request.py
jay_sdk_test/models/health_controller_check200_response.py
jay_sdk_test-0.0.20.dist-info/METADATA
jay_sdk_test-0.0.20.dist-info/WHEEL
jay_sdk_test-0.0.20.dist-info/top_level.txt
jay_sdk_test-0.0.20.dist-info/RECORD
